exppy.py
exppy-0.1.3.dist-info/LICENSE
exppy-0.1.3.dist-info/METADATA
exppy-0.1.3.dist-info/WHEEL
exppy-0.1.3.dist-info/top_level.txt
exppy-0.1.3.dist-info/RECORD
