Metadata-Version: 2.1
Name: exppy
Version: 0.1.3
Summary: Numerical experiments in python
Home-page: https://github.com/mrkwjc/exppy
Author: Marek Wojciechowski
Author-email: mrkwjc@gmail.com
License: MIT
Keywords: doe,numerical experiment
Classifier: Programming Language :: Python :: 2
Classifier: Programming Language :: Python :: 3
Classifier: License :: OSI Approved :: MIT License
Classifier: Operating System :: OS Independent
Requires-Python: >=3.6
License-File: LICENSE
Requires-Dist: numpy
Requires-Dist: pydoe2
